manabase/__init__.py
manabase/__main__.py
manabase/app/__init__.py
manabase/app/cache.py
manabase/app/generate.py
manabase/app/presets.py
manabase/cache.py
manabase/cards.py
manabase/client.py
manabase/colors.py
manabase/constructor.py
manabase/defaults.py
manabase/filler/__init__.py
manabase/filler/distribution.py
manabase/filler/filler.py
manabase/filter/__init__.py
manabase/filter/data.py
manabase/filter/manager.py
manabase/filter/parser.py
manabase/filters/__init__.py
manabase/filters/base.py
manabase/filters/colors.py
manabase/filters/composite.py
manabase/filters/lands/__init__.py
manabase/filters/lands/battle.py
manabase/filters/lands/bond.py
manabase/filters/lands/bounce.py
manabase/filters/lands/check.py
manabase/filters/lands/cycling.py
manabase/filters/lands/fast.py
manabase/filters/lands/fetch.py
manabase/filters/lands/filter.py
manabase/filters/lands/horizon.py
manabase/filters/lands/original.py
manabase/filters/lands/pain.py
manabase/filters/lands/reveal.py
manabase/filters/lands/scry.py
manabase/filters/lands/shock.py
manabase/filters/rocks/__init__.py
manabase/filters/rocks/banner.py
manabase/filters/rocks/cluestone.py
manabase/filters/rocks/crystal.py
manabase/filters/rocks/locket.py
manabase/filters/rocks/obelisk.py
manabase/filters/rocks/signet.py
manabase/filters/rocks/talisman.py
manabase/filters/set.py
manabase/filters/text.py
manabase/formatter.py
manabase/generator.py
manabase/priorities.py
manabase/query.py
manabase/settings.py
manabase-0.3.1.dist-info/entry_points.txt
manabase-0.3.1.dist-info/LICENSE.md
manabase-0.3.1.dist-info/WHEEL
manabase-0.3.1.dist-info/METADATA
manabase-0.3.1.dist-info/RECORD
