Metadata-Version: 2.1
Name: manabase
Version: 0.3.1
Summary: Manabase generator for all your Magic: The Gathering needs.
Home-page: https://github.com/Aphosis/manabase
License: MIT
Author: Aphosis
Author-email: aphosis.github@gmail.com
Requires-Python: >=3.8,<4.0
Classifier: License :: OSI Approved :: MIT License
Classifier: Programming Language :: Python :: 3
Classifier: Programming Language :: Python :: 3.8
Requires-Dist: appdirs (>=1.4.4,<2.0.0)
Requires-Dist: diskcache (>=5.0.3,<6.0.0)
Requires-Dist: parsimonious (>=0.8.1,<0.9.0)
Requires-Dist: pydantic (>=1.7.2,<2.0.0)
Requires-Dist: python-dotenv (>=0.15.0,<0.16.0)
Requires-Dist: pyyaml (>=5.3.1,<6.0.0)
Requires-Dist: requests (>=2.24.0,<3.0.0)
Requires-Dist: typer (>=0.3.2,<0.4.0)
Project-URL: Repository, https://github.com/Aphosis/manabase
